examples/__init__.py
examples/brownian_motion.py
examples/brownian_motion_multifractal_time.py
examples/rs_analysis.py
fractalmarkets/__init__.py
fractalmarkets/mmar/__init__.py
fractalmarkets/mmar/brownian_motion.py
fractalmarkets/mmar/brownian_motion_multifractal_time.py
fractalmarkets/mmar/multiplicative_cascade.py
fractalmarkets/mmar/trading_time_cdf.py
fractalmarkets/rs/__init__.py
fractalmarkets/rs/metrics.py
fractalmarkets/rs/plots.py
fractalmarkets/rs/rs.py
fractalmarkets-1.0.1.dist-info/METADATA
fractalmarkets-1.0.1.dist-info/WHEEL
fractalmarkets-1.0.1.dist-info/top_level.txt
fractalmarkets-1.0.1.dist-info/RECORD
