Metadata-Version: 2.1
Name: fractalmarkets
Version: 1.0.1
Summary: Implementation of Benoit Mandelbrot's Brownian Motion in Multifractal Time and Edgar E. Peter's Fractal Market Analysis.
Home-page: https://github.com/hyperstripe50/fractal-market-analysis
Author: Jona Scott & Daniel Luftspring
Author-email: jrscott.w@gmail.com
License: MIT
Platform: UNKNOWN
Requires-Dist: numpy
Requires-Dist: matplotlib
Requires-Dist: scipy
